{
 "name": "Skip Beat!",
 "shouldNotify": true,
 "lastUpdate": "2024-02-05T05:44:22Z",
 "slug": "skip-beat_110",
 "status": "ongoing",
 "source": "manganel",
 "chapters": [
  {
   "name": 321,
   "slug": null,
   "date": "2024-02-05T05:44:22Z",
   "uri": "https://manganel.me/chapter/skip-beat_110/chapter-321"
  },
  {
   "name": 319,
   "slug": null,
   "date": "2023-12-03T16:29:03Z",
   "uri": "https://manganel.me/chapter/skip-beat_110/chapter-319"
  },
  {
   "name": 318,
   "slug": null,
   "date": "2023-11-08T07:29:14Z",
   "uri": "https://manganel.me/chapter/skip-beat_110/chapter-318"
  },
  {
   "name": 317,
   "slug": null,
   "date": "2023-09-25T05:13:27Z",
   "uri": "https://manganel.me/chapter/skip-beat_110/chapter-317"
  },
  {
   "name": 316,
   "slug": null,
   "date": "2023-09-25T05:13:27Z",
   "uri": "https://manganel.me/chapter/skip-beat_110/chapter-316"
  },
  {
   "name": 315,
   "slug": null,
   "date": "2023-09-25T03:45:03Z",
   "uri": "https://manganel.me/chapter/skip-beat_110/chapter-315"
  },
  {
   "name": 314,
   "slug": null,
   "date": "2023-09-25T03:45:03Z",
   "uri": "https://manganel.me/chapter/skip-beat_110/chapter-314"
  },
  {
   "name": 313,
   "slug": null,
   "date": "2023-09-25T03:28:11Z",
   "uri": "https://manganel.me/chapter/skip-beat_110/chapter-313"
  },
  {
   "name": 312,
   "slug": null,
   "date": "2023-09-25T03:28:11Z",
   "uri": "https://manganel.me/chapter/skip-beat_110/chapter-312"
  },
  {
   "name": 311,
   "slug": null,
   "date": "2023-09-21T03:13:32Z",
   "uri": "https://manganel.me/chapter/skip-beat_110/chapter-311"
  },
  {
   "name": 310,
   "slug": null,
   "date": "2023-08-31T00:47:11Z",
   "uri": "https://manganel.me/chapter/skip-beat_110/chapter-310"
  },
  {
   "name": 309,
   "slug": null,
   "date": "2022-08-30T01:31:22Z",
   "uri": "https://manganel.me/chapter/skip-beat_110/chapter-309"
  },
  {
   "name": 308,
   "slug": null,
   "date": "2022-08-30T01:31:22Z",
   "uri": "https://manganel.me/chapter/skip-beat_110/chapter-308"
  },
  {
   "name": 307,
   "slug": null,
   "date": "2022-06-26T18:56:04Z",
   "uri": "https://manganel.me/chapter/skip-beat_110/chapter-307"
  },
  {
   "name": 306,
   "slug": null,
   "date": "2022-06-06T03:41:03Z",
   "uri": "https://manganel.me/chapter/skip-beat_110/chapter-306"
  },
  {
   "name": 305,
   "slug": null,
   "date": "2022-04-24T23:26:04Z",
   "uri": "https://manganel.me/chapter/skip-beat_110/chapter-305"
  },
  {
   "name": 304,
   "slug": null,
   "date": "2022-03-23T16:56:03Z",
   "uri": "https://manganel.me/chapter/skip-beat_110/chapter-304"
  },
  {
   "name": 303,
   "slug": null,
   "date": "2022-03-01T01:28:18Z",
   "uri": "https://manganel.me/chapter/skip-beat_110/chapter-303"
  },
  {
   "name": 302,
   "slug": null,
   "date": "2022-01-21T20:32:11Z",
   "uri": "https://manganel.me/chapter/skip-beat_110/chapter-302"
  },
  {
   "name": 301,
   "slug": null,
   "date": "2021-12-24T20:16:59Z",
   "uri": "https://manganel.me/chapter/skip-beat_110/chapter-301"
  },
  {
   "name": 300,
   "slug": null,
   "date": "2021-11-24T05:24:54Z",
   "uri": "https://manganel.me/chapter/skip-beat_110/chapter-300"
  },
  {
   "name": 299,
   "slug": null,
   "date": "2021-11-14T23:27:09Z",
   "uri": "https://manganel.me/chapter/skip-beat_110/chapter-299"
  },
  {
   "name": 298,
   "slug": null,
   "date": "2021-11-14T23:27:09Z",
   "uri": "https://manganel.me/chapter/skip-beat_110/chapter-298"
  },
  {
   "name": 297,
   "slug": null,
   "date": "2021-11-14T23:27:09Z",
   "uri": "https://manganel.me/chapter/skip-beat_110/chapter-297"
  },
  {
   "name": 296,
   "slug": null,
   "date": "2021-07-24T04:15:56Z",
   "uri": "https://manganel.me/chapter/skip-beat_110/chapter-296"
  },
  {
   "name": 295,
   "slug": null,
   "date": "2021-07-19T16:46:35Z",
   "uri": "https://manganel.me/chapter/skip-beat_110/chapter-295"
  },
  {
   "name": 294,
   "slug": null,
   "date": "2021-05-28T13:48:06Z",
   "uri": "https://manganel.me/chapter/skip-beat_110/chapter-294"
  },
  {
   "name": 293,
   "slug": null,
   "date": "2021-05-28T13:48:06Z",
   "uri": "https://manganel.me/chapter/skip-beat_110/chapter-293"
  },
  {
   "name": 292,
   "slug": null,
   "date": "2021-05-28T13:48:06Z",
   "uri": "https://manganel.me/chapter/skip-beat_110/chapter-292"
  },
  {
   "name": 291,
   "slug": null,
   "date": "2021-02-20T19:22:29Z",
   "uri": "https://manganel.me/chapter/skip-beat_110/chapter-291"
  },
  {
   "name": 290,
   "slug": null,
   "date": "2021-01-21T10:51:01Z",
   "uri": "https://manganel.me/chapter/skip-beat_110/chapter-290"
  },
  {
   "name": 289,
   "slug": null,
   "date": "2020-12-20T05:53:13Z",
   "uri": "https://manganel.me/chapter/skip-beat_110/chapter-289"
  },
  {
   "name": 288,
   "slug": null,
   "date": "2020-12-08T04:51:36Z",
   "uri": "https://manganel.me/chapter/skip-beat_110/chapter-288"
  },
  {
   "name": 287,
   "slug": null,
   "date": "2020-10-22T02:51:13Z",
   "uri": "https://manganel.me/chapter/skip-beat_110/chapter-287"
  },
  {
   "name": 286,
   "slug": null,
   "date": "2020-09-24T03:47:43Z",
   "uri": "https://manganel.me/chapter/skip-beat_110/chapter-286"
  },
  {
   "name": 285,
   "slug": null,
   "date": "2020-08-22T01:36:30Z",
   "uri": "https://manganel.me/chapter/skip-beat_110/chapter-285"
  },
  {
   "name": 284,
   "slug": null,
   "date": "2020-07-27T06:47:32Z",
   "uri": "https://manganel.me/chapter/skip-beat_110/chapter-284"
  },
  {
   "name": 283,
   "slug": null,
   "date": "2020-06-20T01:34:02Z",
   "uri": "https://manganel.me/chapter/skip-beat_110/chapter-283"
  },
  {
   "name": 282,
   "slug": null,
   "date": "2020-05-21T04:38:29Z",
   "uri": "https://manganel.me/chapter/skip-beat_110/chapter-282"
  },
  {
   "name": 281,
   "slug": null,
   "date": "2020-04-20T22:32:09Z",
   "uri": "https://manganel.me/chapter/skip-beat_110/chapter-281"
  },
  {
   "name": 280,
   "slug": null,
   "date": "2020-03-21T14:00:31Z",
   "uri": "https://manganel.me/chapter/skip-beat_110/chapter-280"
  },
  {
   "name": 279,
   "slug": null,
   "date": "2020-02-21T11:31:04Z",
   "uri": "https://manganel.me/chapter/skip-beat_110/chapter-279"
  },
  {
   "name": 278,
   "slug": null,
   "date": "2020-01-19T18:30:14Z",
   "uri": "https://manganel.me/chapter/skip-beat_110/chapter-278"
  },
  {
   "name": 277,
   "slug": null,
   "date": "2019-12-28T23:15:06Z",
   "uri": "https://manganel.me/chapter/skip-beat_110/chapter-277"
  },
  {
   "name": 276,
   "slug": null,
   "date": "2019-11-21T23:43:03Z",
   "uri": "https://manganel.me/chapter/skip-beat_110/chapter-276"
  },
  {
   "name": 275,
   "slug": null,
   "date": "2019-10-21T03:28:03Z",
   "uri": "https://manganel.me/chapter/skip-beat_110/chapter-275"
  },
  {
   "name": 274,
   "slug": null,
   "date": "2019-09-25T04:43:05Z",
   "uri": "https://manganel.me/chapter/skip-beat_110/chapter-274"
  },
  {
   "name": 273,
   "slug": null,
   "date": "2019-09-05T00:58:04Z",
   "uri": "https://manganel.me/chapter/skip-beat_110/chapter-273"
  },
  {
   "name": 272,
   "slug": null,
   "date": "2019-07-20T21:43:03Z",
   "uri": "https://manganel.me/chapter/skip-beat_110/chapter-272"
  },
  {
   "name": 271,
   "slug": null,
   "date": "2019-06-22T20:58:03Z",
   "uri": "https://manganel.me/chapter/skip-beat_110/chapter-271"
  },
  {
   "name": 270,
   "slug": null,
   "date": "2019-05-21T03:58:03Z",
   "uri": "https://manganel.me/chapter/skip-beat_110/chapter-270"
  },
  {
   "name": 269,
   "slug": null,
   "date": "2019-04-23T15:13:05Z",
   "uri": "https://manganel.me/chapter/skip-beat_110/chapter-269"
  },
  {
   "name": 268,
   "slug": null,
   "date": "2019-03-21T17:43:03Z",
   "uri": "https://manganel.me/chapter/skip-beat_110/chapter-268"
  },
  {
   "name": 267,
   "slug": null,
   "date": "2019-02-21T19:13:03Z",
   "uri": "https://manganel.me/chapter/skip-beat_110/chapter-267"
  },
  {
   "name": 266.5,
   "slug": null,
   "date": "2019-02-10T16:58:04Z",
   "uri": "https://manganel.me/chapter/skip-beat_110/chapter-266.5"
  },
  {
   "name": 266,
   "slug": null,
   "date": "2019-01-28T02:28:04Z",
   "uri": "https://manganel.me/chapter/skip-beat_110/chapter-266"
  },
  {
   "name": 265,
   "slug": null,
   "date": "2018-11-26T15:28:04Z",
   "uri": "https://manganel.me/chapter/skip-beat_110/chapter-265"
  },
  {
   "name": 264,
   "slug": null,
   "date": "2018-10-24T20:43:05Z",
   "uri": "https://manganel.me/chapter/skip-beat_110/chapter-264"
  },
  {
   "name": 263,
   "slug": null,
   "date": "2018-09-25T12:13:24Z",
   "uri": "https://manganel.me/chapter/skip-beat_110/chapter-263"
  },
  {
   "name": 262,
   "slug": null,
   "date": "2018-08-24T05:28:03Z",
   "uri": "https://manganel.me/chapter/skip-beat_110/chapter-262"
  },
  {
   "name": 261,
   "slug": null,
   "date": "2018-07-24T16:00:04Z",
   "uri": "https://manganel.me/chapter/skip-beat_110/chapter-261"
  },
  {
   "name": 260,
   "slug": null,
   "date": "2018-06-22T04:45:04Z",
   "uri": "https://manganel.me/chapter/skip-beat_110/chapter-260"
  },
  {
   "name": 259,
   "slug": null,
   "date": "2018-05-22T01:15:05Z",
   "uri": "https://manganel.me/chapter/skip-beat_110/chapter-259"
  },
  {
   "name": 258,
   "slug": null,
   "date": "2018-04-26T02:30:04Z",
   "uri": "https://manganel.me/chapter/skip-beat_110/chapter-258"
  },
  {
   "name": 257,
   "slug": null,
   "date": "2018-03-28T17:15:15Z",
   "uri": "https://manganel.me/chapter/skip-beat_110/chapter-257"
  },
  {
   "name": 256,
   "slug": null,
   "date": "2018-02-24T02:30:12Z",
   "uri": "https://manganel.me/chapter/skip-beat_110/chapter-256"
  },
  {
   "name": 255,
   "slug": null,
   "date": "2018-02-19T16:15:05Z",
   "uri": "https://manganel.me/chapter/skip-beat_110/chapter-255"
  },
  {
   "name": 254,
   "slug": null,
   "date": "2017-12-22T20:00:03Z",
   "uri": "https://manganel.me/chapter/skip-beat_110/chapter-254"
  },
  {
   "name": 253,
   "slug": null,
   "date": "2017-11-27T13:45:04Z",
   "uri": "https://manganel.me/chapter/skip-beat_110/chapter-253"
  },
  {
   "name": 252,
   "slug": null,
   "date": "2017-10-23T04:46:36Z",
   "uri": "https://manganel.me/chapter/skip-beat_110/chapter-252"
  },
  {
   "name": 251,
   "slug": null,
   "date": "2017-09-27T02:15:05Z",
   "uri": "https://manganel.me/chapter/skip-beat_110/chapter-251"
  },
  {
   "name": 250,
   "slug": null,
   "date": "2017-08-21T06:30:05Z",
   "uri": "https://manganel.me/chapter/skip-beat_110/chapter-250"
  },
  {
   "name": 249,
   "slug": null,
   "date": "2017-06-21T00:00:00Z",
   "uri": "https://manganel.me/chapter/skip-beat_110/chapter-249"
  },
  {
   "name": 248,
   "slug": null,
   "date": "2017-05-21T00:00:00Z",
   "uri": "https://manganel.me/chapter/skip-beat_110/chapter-248"
  },
  {
   "name": 247,
   "slug": null,
   "date": "2017-04-25T00:00:00Z",
   "uri": "https://manganel.me/chapter/skip-beat_110/chapter-247"
  },
  {
   "name": 246,
   "slug": null,
   "date": "2017-03-19T00:00:00Z",
   "uri": "https://manganel.me/chapter/skip-beat_110/chapter-246"
  },
  {
   "name": 245,
   "slug": null,
   "date": "2017-02-22T00:00:00Z",
   "uri": "https://manganel.me/chapter/skip-beat_110/chapter-245"
  },
  {
   "name": 244,
   "slug": null,
   "date": "2017-01-23T00:00:00Z",
   "uri": "https://manganel.me/chapter/skip-beat_110/chapter-244"
  },
  {
   "name": 243,
   "slug": null,
   "date": "2016-12-24T00:00:00Z",
   "uri": "https://manganel.me/chapter/skip-beat_110/chapter-243"
  },
  {
   "name": 242,
   "slug": null,
   "date": "2016-11-20T00:00:00Z",
   "uri": "https://manganel.me/chapter/skip-beat_110/chapter-242"
  },
  {
   "name": 241,
   "slug": null,
   "date": "2016-10-23T00:00:00Z",
   "uri": "https://manganel.me/chapter/skip-beat_110/chapter-241"
  },
  {
   "name": 240,
   "slug": null,
   "date": "2016-09-27T00:00:00Z",
   "uri": "https://manganel.me/chapter/skip-beat_110/chapter-240"
  },
  {
   "name": 239,
   "slug": null,
   "date": "2016-08-23T00:00:00Z",
   "uri": "https://manganel.me/chapter/skip-beat_110/chapter-239"
  },
  {
   "name": 238,
   "slug": null,
   "date": "2016-07-24T00:00:00Z",
   "uri": "https://manganel.me/chapter/skip-beat_110/chapter-238"
  },
  {
   "name": 237,
   "slug": null,
   "date": "2016-06-28T00:00:00Z",
   "uri": "https://manganel.me/chapter/skip-beat_110/chapter-237"
  },
  {
   "name": 236,
   "slug": null,
   "date": "2016-05-25T00:00:00Z",
   "uri": "https://manganel.me/chapter/skip-beat_110/chapter-236"
  },
  {
   "name": 235,
   "slug": null,
   "date": "2016-04-24T00:00:00Z",
   "uri": "https://manganel.me/chapter/skip-beat_110/chapter-235"
  },
  {
   "name": 234,
   "slug": null,
   "date": "2016-03-21T00:00:00Z",
   "uri": "https://manganel.me/chapter/skip-beat_110/chapter-234"
  },
  {
   "name": 233,
   "slug": null,
   "date": "2016-02-22T00:00:00Z",
   "uri": "https://manganel.me/chapter/skip-beat_110/chapter-233"
  },
  {
   "name": 232,
   "slug": null,
   "date": "2016-01-24T00:00:00Z",
   "uri": "https://manganel.me/chapter/skip-beat_110/chapter-232"
  },
  {
   "name": 231,
   "slug": null,
   "date": "2016-01-20T00:00:00Z",
   "uri": "https://manganel.me/chapter/skip-beat_110/chapter-231"
  },
  {
   "name": 230,
   "slug": null,
   "date": "2016-01-20T00:00:00Z",
   "uri": "https://manganel.me/chapter/skip-beat_110/chapter-230"
  },
  {
   "name": 229,
   "slug": null,
   "date": "2016-01-20T00:00:00Z",
   "uri": "https://manganel.me/chapter/skip-beat_110/chapter-229"
  },
  {
   "name": 228,
   "slug": null,
   "date": "2016-01-20T00:00:00Z",
   "uri": "https://manganel.me/chapter/skip-beat_110/chapter-228"
  },
  {
   "name": 227,
   "slug": null,
   "date": "2016-01-20T00:00:00Z",
   "uri": "https://manganel.me/chapter/skip-beat_110/chapter-227"
  },
  {
   "name": 226,
   "slug": null,
   "date": "2016-01-20T00:00:00Z",
   "uri": "https://manganel.me/chapter/skip-beat_110/chapter-226"
  },
  {
   "name": 225.5,
   "slug": null,
   "date": "2017-06-29T00:00:00Z",
   "uri": "https://manganel.me/chapter/skip-beat_110/chapter-225.5"
  },
  {
   "name": 225,
   "slug": null,
   "date": "2016-01-20T00:00:00Z",
   "uri": "https://manganel.me/chapter/skip-beat_110/chapter-225"
  },
  {
   "name": 224,
   "slug": null,
   "date": "2016-01-20T00:00:00Z",
   "uri": "https://manganel.me/chapter/skip-beat_110/chapter-224"
  },
  {
   "name": 223,
   "slug": null,
   "date": "2016-01-20T00:00:00Z",
   "uri": "https://manganel.me/chapter/skip-beat_110/chapter-223"
  },
  {
   "name": 222,
   "slug": null,
   "date": "2016-01-20T00:00:00Z",
   "uri": "https://manganel.me/chapter/skip-beat_110/chapter-222"
  },
  {
   "name": 221,
   "slug": null,
   "date": "2016-01-20T00:00:00Z",
   "uri": "https://manganel.me/chapter/skip-beat_110/chapter-221"
  },
  {
   "name": 220,
   "slug": null,
   "date": "2016-01-20T00:00:00Z",
   "uri": "https://manganel.me/chapter/skip-beat_110/chapter-220"
  },
  {
   "name": 219,
   "slug": null,
   "date": "2016-01-20T00:00:00Z",
   "uri": "https://manganel.me/chapter/skip-beat_110/chapter-219"
  },
  {
   "name": 218,
   "slug": null,
   "date": "2016-01-20T00:00:00Z",
   "uri": "https://manganel.me/chapter/skip-beat_110/chapter-218"
  },
  {
   "name": 217,
   "slug": null,
   "date": "2016-01-20T00:00:00Z",
   "uri": "https://manganel.me/chapter/skip-beat_110/chapter-217"
  },
  {
   "name": 216,
   "slug": null,
   "date": "2016-01-20T00:00:00Z",
   "uri": "https://manganel.me/chapter/skip-beat_110/chapter-216"
  },
  {
   "name": 215,
   "slug": null,
   "date": "2016-01-20T00:00:00Z",
   "uri": "https://manganel.me/chapter/skip-beat_110/chapter-215"
  },
  {
   "name": 214,
   "slug": null,
   "date": "2016-01-20T00:00:00Z",
   "uri": "https://manganel.me/chapter/skip-beat_110/chapter-214"
  },
  {
   "name": 213,
   "slug": null,
   "date": "2016-01-20T00:00:00Z",
   "uri": "https://manganel.me/chapter/skip-beat_110/chapter-213"
  },
  {
   "name": 212.5,
   "slug": null,
   "date": "2014-10-14T00:00:00Z",
   "uri": "https://manganel.me/chapter/skip-beat_110/chapter-212.5"
  },
  {
   "name": 212,
   "slug": null,
   "date": "2016-01-20T00:00:00Z",
   "uri": "https://manganel.me/chapter/skip-beat_110/chapter-212"
  },
  {
   "name": 211,
   "slug": null,
   "date": "2016-01-20T00:00:00Z",
   "uri": "https://manganel.me/chapter/skip-beat_110/chapter-211"
  },
  {
   "name": 210,
   "slug": null,
   "date": "2016-01-20T00:00:00Z",
   "uri": "https://manganel.me/chapter/skip-beat_110/chapter-210"
  },
  {
   "name": 209,
   "slug": null,
   "date": "2016-01-20T00:00:00Z",
   "uri": "https://manganel.me/chapter/skip-beat_110/chapter-209"
  },
  {
   "name": 208,
   "slug": null,
   "date": "2016-01-20T00:00:00Z",
   "uri": "https://manganel.me/chapter/skip-beat_110/chapter-208"
  },
  {
   "name": 207,
   "slug": null,
   "date": "2016-01-20T00:00:00Z",
   "uri": "https://manganel.me/chapter/skip-beat_110/chapter-207"
  },
  {
   "name": 206.5,
   "slug": null,
   "date": "2014-11-17T00:00:00Z",
   "uri": "https://manganel.me/chapter/skip-beat_110/chapter-206.5"
  },
  {
   "name": 206,
   "slug": null,
   "date": "2016-01-20T00:00:00Z",
   "uri": "https://manganel.me/chapter/skip-beat_110/chapter-206"
  },
  {
   "name": 205,
   "slug": null,
   "date": "2016-01-20T00:00:00Z",
   "uri": "https://manganel.me/chapter/skip-beat_110/chapter-205"
  },
  {
   "name": 204,
   "slug": null,
   "date": "2016-01-20T00:00:00Z",
   "uri": "https://manganel.me/chapter/skip-beat_110/chapter-204"
  },
  {
   "name": 203.5,
   "slug": null,
   "date": "2014-05-08T00:00:00Z",
   "uri": "https://manganel.me/chapter/skip-beat_110/chapter-203.5"
  },
  {
   "name": 203,
   "slug": null,
   "date": "2016-01-20T00:00:00Z",
   "uri": "https://manganel.me/chapter/skip-beat_110/chapter-203"
  },
  {
   "name": 202,
   "slug": null,
   "date": "2016-01-20T00:00:00Z",
   "uri": "https://manganel.me/chapter/skip-beat_110/chapter-202"
  },
  {
   "name": 201,
   "slug": null,
   "date": "2016-01-20T00:00:00Z",
   "uri": "https://manganel.me/chapter/skip-beat_110/chapter-201"
  },
  {
   "name": 200.5,
   "slug": null,
   "date": "2014-11-17T00:00:00Z",
   "uri": "https://manganel.me/chapter/skip-beat_110/chapter-200.5"
  },
  {
   "name": 200,
   "slug": null,
   "date": "2016-01-20T00:00:00Z",
   "uri": "https://manganel.me/chapter/skip-beat_110/chapter-200"
  },
  {
   "name": 199,
   "slug": null,
   "date": "2016-01-20T00:00:00Z",
   "uri": "https://manganel.me/chapter/skip-beat_110/chapter-199"
  },
  {
   "name": 198,
   "slug": null,
   "date": "2016-01-20T00:00:00Z",
   "uri": "https://manganel.me/chapter/skip-beat_110/chapter-198"
  },
  {
   "name": 197,
   "slug": null,
   "date": "2016-01-20T00:00:00Z",
   "uri": "https://manganel.me/chapter/skip-beat_110/chapter-197"
  },
  {
   "name": 196,
   "slug": null,
   "date": "2016-01-20T00:00:00Z",
   "uri": "https://manganel.me/chapter/skip-beat_110/chapter-196"
  },
  {
   "name": 195,
   "slug": null,
   "date": "2016-01-20T00:00:00Z",
   "uri": "https://manganel.me/chapter/skip-beat_110/chapter-195"
  },
  {
   "name": 194,
   "slug": null,
   "date": "2016-01-20T00:00:00Z",
   "uri": "https://manganel.me/chapter/skip-beat_110/chapter-194"
  },
  {
   "name": 193,
   "slug": null,
   "date": "2016-01-20T00:00:00Z",
   "uri": "https://manganel.me/chapter/skip-beat_110/chapter-193"
  },
  {
   "name": 192,
   "slug": null,
   "date": "2016-01-20T00:00:00Z",
   "uri": "https://manganel.me/chapter/skip-beat_110/chapter-192"
  },
  {
   "name": 191,
   "slug": null,
   "date": "2016-01-20T00:00:00Z",
   "uri": "https://manganel.me/chapter/skip-beat_110/chapter-191"
  },
  {
   "name": 190,
   "slug": null,
   "date": "2016-01-20T00:00:00Z",
   "uri": "https://manganel.me/chapter/skip-beat_110/chapter-190"
  },
  {
   "name": 189,
   "slug": null,
   "date": "2016-01-20T00:00:00Z",
   "uri": "https://manganel.me/chapter/skip-beat_110/chapter-189"
  },
  {
   "name": 188.5,
   "slug": null,
   "date": "2014-11-17T00:00:00Z",
   "uri": "https://manganel.me/chapter/skip-beat_110/chapter-188.5"
  },
  {
   "name": 188,
   "slug": null,
   "date": "2016-01-20T00:00:00Z",
   "uri": "https://manganel.me/chapter/skip-beat_110/chapter-188"
  },
  {
   "name": 187,
   "slug": null,
   "date": "2016-01-20T00:00:00Z",
   "uri": "https://manganel.me/chapter/skip-beat_110/chapter-187"
  },
  {
   "name": 186,
   "slug": null,
   "date": "2016-01-20T00:00:00Z",
   "uri": "https://manganel.me/chapter/skip-beat_110/chapter-186"
  },
  {
   "name": 185,
   "slug": null,
   "date": "2016-01-20T00:00:00Z",
   "uri": "https://manganel.me/chapter/skip-beat_110/chapter-185"
  },
  {
   "name": 184,
   "slug": null,
   "date": "2016-01-20T00:00:00Z",
   "uri": "https://manganel.me/chapter/skip-beat_110/chapter-184"
  },
  {
   "name": 183,
   "slug": null,
   "date": "2016-01-20T00:00:00Z",
   "uri": "https://manganel.me/chapter/skip-beat_110/chapter-183"
  },
  {
   "name": 182,
   "slug": null,
   "date": "2016-01-20T00:00:00Z",
   "uri": "https://manganel.me/chapter/skip-beat_110/chapter-182"
  },
  {
   "name": 181,
   "slug": null,
   "date": "2016-01-20T00:00:00Z",
   "uri": "https://manganel.me/chapter/skip-beat_110/chapter-181"
  },
  {
   "name": 180,
   "slug": null,
   "date": "2016-01-20T00:00:00Z",
   "uri": "https://manganel.me/chapter/skip-beat_110/chapter-180"
  },
  {
   "name": 179,
   "slug": null,
   "date": "2016-01-20T00:00:00Z",
   "uri": "https://manganel.me/chapter/skip-beat_110/chapter-179"
  },
  {
   "name": 178,
   "slug": null,
   "date": "2016-01-20T00:00:00Z",
   "uri": "https://manganel.me/chapter/skip-beat_110/chapter-178"
  },
  {
   "name": 177,
   "slug": null,
   "date": "2016-01-20T00:00:00Z",
   "uri": "https://manganel.me/chapter/skip-beat_110/chapter-177"
  },
  {
   "name": 176,
   "slug": null,
   "date": "2016-01-20T00:00:00Z",
   "uri": "https://manganel.me/chapter/skip-beat_110/chapter-176"
  },
  {
   "name": 175,
   "slug": null,
   "date": "2016-01-20T00:00:00Z",
   "uri": "https://manganel.me/chapter/skip-beat_110/chapter-175"
  },
  {
   "name": 174,
   "slug": null,
   "date": "2016-01-20T00:00:00Z",
   "uri": "https://manganel.me/chapter/skip-beat_110/chapter-174"
  },
  {
   "name": 173,
   "slug": null,
   "date": "2016-01-20T00:00:00Z",
   "uri": "https://manganel.me/chapter/skip-beat_110/chapter-173"
  },
  {
   "name": 172,
   "slug": null,
   "date": "2016-01-20T00:00:00Z",
   "uri": "https://manganel.me/chapter/skip-beat_110/chapter-172"
  },
  {
   "name": 171,
   "slug": null,
   "date": "2016-01-20T00:00:00Z",
   "uri": "https://manganel.me/chapter/skip-beat_110/chapter-171"
  },
  {
   "name": 170,
   "slug": null,
   "date": "2016-01-20T00:00:00Z",
   "uri": "https://manganel.me/chapter/skip-beat_110/chapter-170"
  },
  {
   "name": 169,
   "slug": null,
   "date": "2016-01-20T00:00:00Z",
   "uri": "https://manganel.me/chapter/skip-beat_110/chapter-169"
  },
  {
   "name": 168,
   "slug": null,
   "date": "2016-01-20T00:00:00Z",
   "uri": "https://manganel.me/chapter/skip-beat_110/chapter-168"
  },
  {
   "name": 167,
   "slug": null,
   "date": "2016-01-20T00:00:00Z",
   "uri": "https://manganel.me/chapter/skip-beat_110/chapter-167"
  },
  {
   "name": 166,
   "slug": null,
   "date": "2016-01-20T00:00:00Z",
   "uri": "https://manganel.me/chapter/skip-beat_110/chapter-166"
  },
  {
   "name": 165,
   "slug": null,
   "date": "2016-01-20T00:00:00Z",
   "uri": "https://manganel.me/chapter/skip-beat_110/chapter-165"
  },
  {
   "name": 164,
   "slug": null,
   "date": "2016-01-20T00:00:00Z",
   "uri": "https://manganel.me/chapter/skip-beat_110/chapter-164"
  },
  {
   "name": 163,
   "slug": null,
   "date": "2016-01-20T00:00:00Z",
   "uri": "https://manganel.me/chapter/skip-beat_110/chapter-163"
  },
  {
   "name": 162,
   "slug": null,
   "date": "2016-01-20T00:00:00Z",
   "uri": "https://manganel.me/chapter/skip-beat_110/chapter-162"
  },
  {
   "name": 161,
   "slug": null,
   "date": "2016-01-20T00:00:00Z",
   "uri": "https://manganel.me/chapter/skip-beat_110/chapter-161"
  },
  {
   "name": 160,
   "slug": null,
   "date": "2016-01-20T00:00:00Z",
   "uri": "https://manganel.me/chapter/skip-beat_110/chapter-160"
  },
  {
   "name": 159,
   "slug": null,
   "date": "2016-01-20T00:00:00Z",
   "uri": "https://manganel.me/chapter/skip-beat_110/chapter-159"
  },
  {
   "name": 158,
   "slug": null,
   "date": "2016-01-20T00:00:00Z",
   "uri": "https://manganel.me/chapter/skip-beat_110/chapter-158"
  },
  {
   "name": 157,
   "slug": null,
   "date": "2016-01-20T00:00:00Z",
   "uri": "https://manganel.me/chapter/skip-beat_110/chapter-157"
  },
  {
   "name": 156,
   "slug": null,
   "date": "2016-01-20T00:00:00Z",
   "uri": "https://manganel.me/chapter/skip-beat_110/chapter-156"
  },
  {
   "name": 155,
   "slug": null,
   "date": "2016-01-20T00:00:00Z",
   "uri": "https://manganel.me/chapter/skip-beat_110/chapter-155"
  },
  {
   "name": 154,
   "slug": null,
   "date": "2016-01-20T00:00:00Z",
   "uri": "https://manganel.me/chapter/skip-beat_110/chapter-154"
  },
  {
   "name": 153,
   "slug": null,
   "date": "2016-01-20T00:00:00Z",
   "uri": "https://manganel.me/chapter/skip-beat_110/chapter-153"
  },
  {
   "name": 152,
   "slug": null,
   "date": "2016-01-20T00:00:00Z",
   "uri": "https://manganel.me/chapter/skip-beat_110/chapter-152"
  },
  {
   "name": 151,
   "slug": null,
   "date": "2016-01-20T00:00:00Z",
   "uri": "https://manganel.me/chapter/skip-beat_110/chapter-151"
  },
  {
   "name": 150.5,
   "slug": null,
   "date": "2018-05-21T08:50:41Z",
   "uri": "https://manganel.me/chapter/skip-beat_110/chapter-150.5"
  },
  {
   "name": 150,
   "slug": null,
   "date": "2016-01-20T00:00:00Z",
   "uri": "https://manganel.me/chapter/skip-beat_110/chapter-150"
  },
  {
   "name": 149,
   "slug": null,
   "date": "2016-01-20T00:00:00Z",
   "uri": "https://manganel.me/chapter/skip-beat_110/chapter-149"
  },
  {
   "name": 148,
   "slug": null,
   "date": "2016-01-20T00:00:00Z",
   "uri": "https://manganel.me/chapter/skip-beat_110/chapter-148"
  },
  {
   "name": 147,
   "slug": null,
   "date": "2016-01-20T00:00:00Z",
   "uri": "https://manganel.me/chapter/skip-beat_110/chapter-147"
  },
  {
   "name": 146,
   "slug": null,
   "date": "2016-01-20T00:00:00Z",
   "uri": "https://manganel.me/chapter/skip-beat_110/chapter-146"
  },
  {
   "name": 145,
   "slug": null,
   "date": "2016-01-20T00:00:00Z",
   "uri": "https://manganel.me/chapter/skip-beat_110/chapter-145"
  },
  {
   "name": 144.5,
   "slug": null,
   "date": "2014-11-17T00:00:00Z",
   "uri": "https://manganel.me/chapter/skip-beat_110/chapter-144.5"
  },
  {
   "name": 144,
   "slug": null,
   "date": "2016-01-20T00:00:00Z",
   "uri": "https://manganel.me/chapter/skip-beat_110/chapter-144"
  },
  {
   "name": 143,
   "slug": null,
   "date": "2016-01-20T00:00:00Z",
   "uri": "https://manganel.me/chapter/skip-beat_110/chapter-143"
  },
  {
   "name": 142,
   "slug": null,
   "date": "2016-01-20T00:00:00Z",
   "uri": "https://manganel.me/chapter/skip-beat_110/chapter-142"
  },
  {
   "name": 141,
   "slug": null,
   "date": "2016-01-20T00:00:00Z",
   "uri": "https://manganel.me/chapter/skip-beat_110/chapter-141"
  },
  {
   "name": 140,
   "slug": null,
   "date": "2016-01-20T00:00:00Z",
   "uri": "https://manganel.me/chapter/skip-beat_110/chapter-140"
  },
  {
   "name": 139,
   "slug": null,
   "date": "2016-01-20T00:00:00Z",
   "uri": "https://manganel.me/chapter/skip-beat_110/chapter-139"
  },
  {
   "name": 138,
   "slug": null,
   "date": "2016-01-20T00:00:00Z",
   "uri": "https://manganel.me/chapter/skip-beat_110/chapter-138"
  },
  {
   "name": 137,
   "slug": null,
   "date": "2016-01-20T00:00:00Z",
   "uri": "https://manganel.me/chapter/skip-beat_110/chapter-137"
  },
  {
   "name": 136,
   "slug": null,
   "date": "2016-01-20T00:00:00Z",
   "uri": "https://manganel.me/chapter/skip-beat_110/chapter-136"
  },
  {
   "name": 135,
   "slug": null,
   "date": "2016-01-20T00:00:00Z",
   "uri": "https://manganel.me/chapter/skip-beat_110/chapter-135"
  },
  {
   "name": 134,
   "slug": null,
   "date": "2016-01-20T00:00:00Z",
   "uri": "https://manganel.me/chapter/skip-beat_110/chapter-134"
  },
  {
   "name": 133,
   "slug": null,
   "date": "2016-01-20T00:00:00Z",
   "uri": "https://manganel.me/chapter/skip-beat_110/chapter-133"
  },
  {
   "name": 132,
   "slug": null,
   "date": "2016-01-20T00:00:00Z",
   "uri": "https://manganel.me/chapter/skip-beat_110/chapter-132"
  },
  {
   "name": 131.5,
   "slug": null,
   "date": "2008-11-26T00:00:00Z",
   "uri": "https://manganel.me/chapter/skip-beat_110/chapter-131.5"
  },
  {
   "name": 131,
   "slug": null,
   "date": "2016-01-20T00:00:00Z",
   "uri": "https://manganel.me/chapter/skip-beat_110/chapter-131"
  },
  {
   "name": 130,
   "slug": null,
   "date": "2016-01-20T00:00:00Z",
   "uri": "https://manganel.me/chapter/skip-beat_110/chapter-130"
  },
  {
   "name": 129,
   "slug": null,
   "date": "2016-01-20T00:00:00Z",
   "uri": "https://manganel.me/chapter/skip-beat_110/chapter-129"
  },
  {
   "name": 128,
   "slug": null,
   "date": "2016-01-20T00:00:00Z",
   "uri": "https://manganel.me/chapter/skip-beat_110/chapter-128"
  },
  {
   "name": 127,
   "slug": null,
   "date": "2016-01-20T00:00:00Z",
   "uri": "https://manganel.me/chapter/skip-beat_110/chapter-127"
  },
  {
   "name": 126,
   "slug": null,
   "date": "2016-01-20T00:00:00Z",
   "uri": "https://manganel.me/chapter/skip-beat_110/chapter-126"
  },
  {
   "name": 125,
   "slug": null,
   "date": "2016-01-20T00:00:00Z",
   "uri": "https://manganel.me/chapter/skip-beat_110/chapter-125"
  },
  {
   "name": 124,
   "slug": null,
   "date": "2016-01-20T00:00:00Z",
   "uri": "https://manganel.me/chapter/skip-beat_110/chapter-124"
  },
  {
   "name": 123,
   "slug": null,
   "date": "2016-01-20T00:00:00Z",
   "uri": "https://manganel.me/chapter/skip-beat_110/chapter-123"
  },
  {
   "name": 122,
   "slug": null,
   "date": "2016-01-20T00:00:00Z",
   "uri": "https://manganel.me/chapter/skip-beat_110/chapter-122"
  },
  {
   "name": 121,
   "slug": null,
   "date": "2016-01-20T00:00:00Z",
   "uri": "https://manganel.me/chapter/skip-beat_110/chapter-121"
  },
  {
   "name": 120,
   "slug": null,
   "date": "2016-01-20T00:00:00Z",
   "uri": "https://manganel.me/chapter/skip-beat_110/chapter-120"
  },
  {
   "name": 119,
   "slug": null,
   "date": "2016-01-20T00:00:00Z",
   "uri": "https://manganel.me/chapter/skip-beat_110/chapter-119"
  },
  {
   "name": 118,
   "slug": null,
   "date": "2016-01-20T00:00:00Z",
   "uri": "https://manganel.me/chapter/skip-beat_110/chapter-118"
  },
  {
   "name": 117,
   "slug": null,
   "date": "2016-01-20T00:00:00Z",
   "uri": "https://manganel.me/chapter/skip-beat_110/chapter-117"
  },
  {
   "name": 116,
   "slug": null,
   "date": "2016-01-20T00:00:00Z",
   "uri": "https://manganel.me/chapter/skip-beat_110/chapter-116"
  },
  {
   "name": 115,
   "slug": null,
   "date": "2016-01-20T00:00:00Z",
   "uri": "https://manganel.me/chapter/skip-beat_110/chapter-115"
  },
  {
   "name": 114,
   "slug": null,
   "date": "2016-01-20T00:00:00Z",
   "uri": "https://manganel.me/chapter/skip-beat_110/chapter-114"
  },
  {
   "name": 113,
   "slug": null,
   "date": "2016-01-20T00:00:00Z",
   "uri": "https://manganel.me/chapter/skip-beat_110/chapter-113"
  },
  {
   "name": 112,
   "slug": null,
   "date": "2016-01-20T00:00:00Z",
   "uri": "https://manganel.me/chapter/skip-beat_110/chapter-112"
  },
  {
   "name": 111,
   "slug": null,
   "date": "2016-01-20T00:00:00Z",
   "uri": "https://manganel.me/chapter/skip-beat_110/chapter-111"
  },
  {
   "name": 110,
   "slug": null,
   "date": "2016-01-20T00:00:00Z",
   "uri": "https://manganel.me/chapter/skip-beat_110/chapter-110"
  },
  {
   "name": 109,
   "slug": null,
   "date": "2016-01-20T00:00:00Z",
   "uri": "https://manganel.me/chapter/skip-beat_110/chapter-109"
  },
  {
   "name": 108,
   "slug": null,
   "date": "2016-01-20T00:00:00Z",
   "uri": "https://manganel.me/chapter/skip-beat_110/chapter-108"
  },
  {
   "name": 107,
   "slug": null,
   "date": "2016-01-20T00:00:00Z",
   "uri": "https://manganel.me/chapter/skip-beat_110/chapter-107"
  },
  {
   "name": 106,
   "slug": null,
   "date": "2016-01-20T00:00:00Z",
   "uri": "https://manganel.me/chapter/skip-beat_110/chapter-106"
  },
  {
   "name": 105,
   "slug": null,
   "date": "2016-01-20T00:00:00Z",
   "uri": "https://manganel.me/chapter/skip-beat_110/chapter-105"
  },
  {
   "name": 104,
   "slug": null,
   "date": "2016-01-20T00:00:00Z",
   "uri": "https://manganel.me/chapter/skip-beat_110/chapter-104"
  },
  {
   "name": 103,
   "slug": null,
   "date": "2016-01-20T00:00:00Z",
   "uri": "https://manganel.me/chapter/skip-beat_110/chapter-103"
  },
  {
   "name": 102,
   "slug": null,
   "date": "2016-01-20T00:00:00Z",
   "uri": "https://manganel.me/chapter/skip-beat_110/chapter-102"
  },
  {
   "name": 101,
   "slug": null,
   "date": "2016-01-20T00:00:00Z",
   "uri": "https://manganel.me/chapter/skip-beat_110/chapter-101"
  },
  {
   "name": 100,
   "slug": null,
   "date": "2016-01-20T00:00:00Z",
   "uri": "https://manganel.me/chapter/skip-beat_110/chapter-100"
  },
  {
   "name": 99,
   "slug": null,
   "date": "2016-01-20T00:00:00Z",
   "uri": "https://manganel.me/chapter/skip-beat_110/chapter-99"
  },
  {
   "name": 98,
   "slug": null,
   "date": "2016-01-20T00:00:00Z",
   "uri": "https://manganel.me/chapter/skip-beat_110/chapter-98"
  },
  {
   "name": 97,
   "slug": null,
   "date": "2016-01-20T00:00:00Z",
   "uri": "https://manganel.me/chapter/skip-beat_110/chapter-97"
  },
  {
   "name": 96,
   "slug": null,
   "date": "2016-01-20T00:00:00Z",
   "uri": "https://manganel.me/chapter/skip-beat_110/chapter-96"
  },
  {
   "name": 95,
   "slug": null,
   "date": "2016-01-20T00:00:00Z",
   "uri": "https://manganel.me/chapter/skip-beat_110/chapter-95"
  },
  {
   "name": 94,
   "slug": null,
   "date": "2016-01-20T00:00:00Z",
   "uri": "https://manganel.me/chapter/skip-beat_110/chapter-94"
  },
  {
   "name": 93,
   "slug": null,
   "date": "2016-01-20T00:00:00Z",
   "uri": "https://manganel.me/chapter/skip-beat_110/chapter-93"
  },
  {
   "name": 92,
   "slug": null,
   "date": "2016-01-20T00:00:00Z",
   "uri": "https://manganel.me/chapter/skip-beat_110/chapter-92"
  },
  {
   "name": 91,
   "slug": null,
   "date": "2016-01-20T00:00:00Z",
   "uri": "https://manganel.me/chapter/skip-beat_110/chapter-91"
  },
  {
   "name": 90,
   "slug": null,
   "date": "2016-01-20T00:00:00Z",
   "uri": "https://manganel.me/chapter/skip-beat_110/chapter-90"
  },
  {
   "name": 89,
   "slug": null,
   "date": "2016-01-20T00:00:00Z",
   "uri": "https://manganel.me/chapter/skip-beat_110/chapter-89"
  },
  {
   "name": 88,
   "slug": null,
   "date": "2016-01-20T00:00:00Z",
   "uri": "https://manganel.me/chapter/skip-beat_110/chapter-88"
  },
  {
   "name": 87,
   "slug": null,
   "date": "2016-01-20T00:00:00Z",
   "uri": "https://manganel.me/chapter/skip-beat_110/chapter-87"
  },
  {
   "name": 86,
   "slug": null,
   "date": "2016-01-20T00:00:00Z",
   "uri": "https://manganel.me/chapter/skip-beat_110/chapter-86"
  },
  {
   "name": 85,
   "slug": null,
   "date": "2016-01-20T00:00:00Z",
   "uri": "https://manganel.me/chapter/skip-beat_110/chapter-85"
  },
  {
   "name": 84,
   "slug": null,
   "date": "2016-01-20T00:00:00Z",
   "uri": "https://manganel.me/chapter/skip-beat_110/chapter-84"
  },
  {
   "name": 83,
   "slug": null,
   "date": "2016-01-20T00:00:00Z",
   "uri": "https://manganel.me/chapter/skip-beat_110/chapter-83"
  },
  {
   "name": 82,
   "slug": null,
   "date": "2016-01-20T00:00:00Z",
   "uri": "https://manganel.me/chapter/skip-beat_110/chapter-82"
  },
  {
   "name": 81,
   "slug": null,
   "date": "2016-01-20T00:00:00Z",
   "uri": "https://manganel.me/chapter/skip-beat_110/chapter-81"
  },
  {
   "name": 80,
   "slug": null,
   "date": "2016-01-20T00:00:00Z",
   "uri": "https://manganel.me/chapter/skip-beat_110/chapter-80"
  },
  {
   "name": 79,
   "slug": null,
   "date": "2016-01-20T00:00:00Z",
   "uri": "https://manganel.me/chapter/skip-beat_110/chapter-79"
  },
  {
   "name": 78,
   "slug": null,
   "date": "2016-01-20T00:00:00Z",
   "uri": "https://manganel.me/chapter/skip-beat_110/chapter-78"
  },
  {
   "name": 77,
   "slug": null,
   "date": "2016-01-20T00:00:00Z",
   "uri": "https://manganel.me/chapter/skip-beat_110/chapter-77"
  },
  {
   "name": 76,
   "slug": null,
   "date": "2016-01-20T00:00:00Z",
   "uri": "https://manganel.me/chapter/skip-beat_110/chapter-76"
  },
  {
   "name": 75,
   "slug": null,
   "date": "2016-01-20T00:00:00Z",
   "uri": "https://manganel.me/chapter/skip-beat_110/chapter-75"
  },
  {
   "name": 74,
   "slug": null,
   "date": "2016-01-20T00:00:00Z",
   "uri": "https://manganel.me/chapter/skip-beat_110/chapter-74"
  },
  {
   "name": 73,
   "slug": null,
   "date": "2016-01-20T00:00:00Z",
   "uri": "https://manganel.me/chapter/skip-beat_110/chapter-73"
  },
  {
   "name": 72,
   "slug": null,
   "date": "2016-01-20T00:00:00Z",
   "uri": "https://manganel.me/chapter/skip-beat_110/chapter-72"
  },
  {
   "name": 71,
   "slug": null,
   "date": "2016-01-20T00:00:00Z",
   "uri": "https://manganel.me/chapter/skip-beat_110/chapter-71"
  },
  {
   "name": 70,
   "slug": null,
   "date": "2016-01-20T00:00:00Z",
   "uri": "https://manganel.me/chapter/skip-beat_110/chapter-70"
  },
  {
   "name": 69,
   "slug": null,
   "date": "2016-01-20T00:00:00Z",
   "uri": "https://manganel.me/chapter/skip-beat_110/chapter-69"
  },
  {
   "name": 68,
   "slug": null,
   "date": "2016-01-20T00:00:00Z",
   "uri": "https://manganel.me/chapter/skip-beat_110/chapter-68"
  },
  {
   "name": 67,
   "slug": null,
   "date": "2016-01-20T00:00:00Z",
   "uri": "https://manganel.me/chapter/skip-beat_110/chapter-67"
  },
  {
   "name": 66.5,
   "slug": null,
   "date": "2014-11-17T00:00:00Z",
   "uri": "https://manganel.me/chapter/skip-beat_110/chapter-66.5"
  },
  {
   "name": 66,
   "slug": null,
   "date": "2016-01-20T00:00:00Z",
   "uri": "https://manganel.me/chapter/skip-beat_110/chapter-66"
  },
  {
   "name": 65,
   "slug": null,
   "date": "2016-01-20T00:00:00Z",
   "uri": "https://manganel.me/chapter/skip-beat_110/chapter-65"
  },
  {
   "name": 64,
   "slug": null,
   "date": "2016-01-20T00:00:00Z",
   "uri": "https://manganel.me/chapter/skip-beat_110/chapter-64"
  },
  {
   "name": 63,
   "slug": null,
   "date": "2016-01-20T00:00:00Z",
   "uri": "https://manganel.me/chapter/skip-beat_110/chapter-63"
  },
  {
   "name": 62,
   "slug": null,
   "date": "2016-01-20T00:00:00Z",
   "uri": "https://manganel.me/chapter/skip-beat_110/chapter-62"
  },
  {
   "name": 61,
   "slug": null,
   "date": "2016-01-20T00:00:00Z",
   "uri": "https://manganel.me/chapter/skip-beat_110/chapter-61"
  },
  {
   "name": 60,
   "slug": null,
   "date": "2016-01-20T00:00:00Z",
   "uri": "https://manganel.me/chapter/skip-beat_110/chapter-60"
  },
  {
   "name": 59,
   "slug": null,
   "date": "2016-01-20T00:00:00Z",
   "uri": "https://manganel.me/chapter/skip-beat_110/chapter-59"
  },
  {
   "name": 58,
   "slug": null,
   "date": "2016-01-20T00:00:00Z",
   "uri": "https://manganel.me/chapter/skip-beat_110/chapter-58"
  },
  {
   "name": 57,
   "slug": null,
   "date": "2016-01-20T00:00:00Z",
   "uri": "https://manganel.me/chapter/skip-beat_110/chapter-57"
  },
  {
   "name": 56,
   "slug": null,
   "date": "2016-01-20T00:00:00Z",
   "uri": "https://manganel.me/chapter/skip-beat_110/chapter-56"
  },
  {
   "name": 55,
   "slug": null,
   "date": "2016-01-20T00:00:00Z",
   "uri": "https://manganel.me/chapter/skip-beat_110/chapter-55"
  },
  {
   "name": 54,
   "slug": null,
   "date": "2016-01-20T00:00:00Z",
   "uri": "https://manganel.me/chapter/skip-beat_110/chapter-54"
  },
  {
   "name": 53,
   "slug": null,
   "date": "2016-01-20T00:00:00Z",
   "uri": "https://manganel.me/chapter/skip-beat_110/chapter-53"
  },
  {
   "name": 52,
   "slug": null,
   "date": "2016-01-20T00:00:00Z",
   "uri": "https://manganel.me/chapter/skip-beat_110/chapter-52"
  },
  {
   "name": 51,
   "slug": null,
   "date": "2016-01-20T00:00:00Z",
   "uri": "https://manganel.me/chapter/skip-beat_110/chapter-51"
  },
  {
   "name": 50,
   "slug": null,
   "date": "2016-01-20T00:00:00Z",
   "uri": "https://manganel.me/chapter/skip-beat_110/chapter-50"
  },
  {
   "name": 49,
   "slug": null,
   "date": "2016-01-20T00:00:00Z",
   "uri": "https://manganel.me/chapter/skip-beat_110/chapter-49"
  },
  {
   "name": 48,
   "slug": null,
   "date": "2016-01-20T00:00:00Z",
   "uri": "https://manganel.me/chapter/skip-beat_110/chapter-48"
  },
  {
   "name": 47,
   "slug": null,
   "date": "2016-01-20T00:00:00Z",
   "uri": "https://manganel.me/chapter/skip-beat_110/chapter-47"
  },
  {
   "name": 46,
   "slug": null,
   "date": "2016-01-20T00:00:00Z",
   "uri": "https://manganel.me/chapter/skip-beat_110/chapter-46"
  },
  {
   "name": 45,
   "slug": null,
   "date": "2016-01-20T00:00:00Z",
   "uri": "https://manganel.me/chapter/skip-beat_110/chapter-45"
  },
  {
   "name": 44,
   "slug": null,
   "date": "2016-01-20T00:00:00Z",
   "uri": "https://manganel.me/chapter/skip-beat_110/chapter-44"
  },
  {
   "name": 43,
   "slug": null,
   "date": "2016-01-20T00:00:00Z",
   "uri": "https://manganel.me/chapter/skip-beat_110/chapter-43"
  },
  {
   "name": 42,
   "slug": null,
   "date": "2016-01-20T00:00:00Z",
   "uri": "https://manganel.me/chapter/skip-beat_110/chapter-42"
  },
  {
   "name": 41,
   "slug": null,
   "date": "2016-01-20T00:00:00Z",
   "uri": "https://manganel.me/chapter/skip-beat_110/chapter-41"
  },
  {
   "name": 40,
   "slug": null,
   "date": "2016-01-20T00:00:00Z",
   "uri": "https://manganel.me/chapter/skip-beat_110/chapter-40"
  },
  {
   "name": 39,
   "slug": null,
   "date": "2016-01-20T00:00:00Z",
   "uri": "https://manganel.me/chapter/skip-beat_110/chapter-39"
  },
  {
   "name": 38,
   "slug": null,
   "date": "2016-01-20T00:00:00Z",
   "uri": "https://manganel.me/chapter/skip-beat_110/chapter-38"
  },
  {
   "name": 37,
   "slug": null,
   "date": "2016-01-20T00:00:00Z",
   "uri": "https://manganel.me/chapter/skip-beat_110/chapter-37"
  },
  {
   "name": 36,
   "slug": null,
   "date": "2016-01-20T00:00:00Z",
   "uri": "https://manganel.me/chapter/skip-beat_110/chapter-36"
  },
  {
   "name": 35,
   "slug": null,
   "date": "2016-01-20T00:00:00Z",
   "uri": "https://manganel.me/chapter/skip-beat_110/chapter-35"
  },
  {
   "name": 34,
   "slug": null,
   "date": "2016-01-20T00:00:00Z",
   "uri": "https://manganel.me/chapter/skip-beat_110/chapter-34"
  },
  {
   "name": 33,
   "slug": null,
   "date": "2016-01-20T00:00:00Z",
   "uri": "https://manganel.me/chapter/skip-beat_110/chapter-33"
  },
  {
   "name": 32,
   "slug": null,
   "date": "2016-01-20T00:00:00Z",
   "uri": "https://manganel.me/chapter/skip-beat_110/chapter-32"
  },
  {
   "name": 31.5,
   "slug": null,
   "date": "2014-11-17T00:00:00Z",
   "uri": "https://manganel.me/chapter/skip-beat_110/chapter-31.5"
  },
  {
   "name": 31,
   "slug": null,
   "date": "2016-01-20T00:00:00Z",
   "uri": "https://manganel.me/chapter/skip-beat_110/chapter-31"
  },
  {
   "name": 30,
   "slug": null,
   "date": "2016-01-20T00:00:00Z",
   "uri": "https://manganel.me/chapter/skip-beat_110/chapter-30"
  },
  {
   "name": 29,
   "slug": null,
   "date": "2016-01-20T00:00:00Z",
   "uri": "https://manganel.me/chapter/skip-beat_110/chapter-29"
  },
  {
   "name": 28,
   "slug": null,
   "date": "2016-01-20T00:00:00Z",
   "uri": "https://manganel.me/chapter/skip-beat_110/chapter-28"
  },
  {
   "name": 27,
   "slug": null,
   "date": "2016-01-20T00:00:00Z",
   "uri": "https://manganel.me/chapter/skip-beat_110/chapter-27"
  },
  {
   "name": 26,
   "slug": null,
   "date": "2016-01-20T00:00:00Z",
   "uri": "https://manganel.me/chapter/skip-beat_110/chapter-26"
  },
  {
   "name": 25,
   "slug": null,
   "date": "2016-01-20T00:00:00Z",
   "uri": "https://manganel.me/chapter/skip-beat_110/chapter-25"
  },
  {
   "name": 24,
   "slug": null,
   "date": "2016-01-20T00:00:00Z",
   "uri": "https://manganel.me/chapter/skip-beat_110/chapter-24"
  },
  {
   "name": 23,
   "slug": null,
   "date": "2016-01-20T00:00:00Z",
   "uri": "https://manganel.me/chapter/skip-beat_110/chapter-23"
  },
  {
   "name": 22,
   "slug": null,
   "date": "2016-01-20T00:00:00Z",
   "uri": "https://manganel.me/chapter/skip-beat_110/chapter-22"
  },
  {
   "name": 21,
   "slug": null,
   "date": "2016-01-20T00:00:00Z",
   "uri": "https://manganel.me/chapter/skip-beat_110/chapter-21"
  },
  {
   "name": 20,
   "slug": null,
   "date": "2016-01-20T00:00:00Z",
   "uri": "https://manganel.me/chapter/skip-beat_110/chapter-20"
  },
  {
   "name": 19,
   "slug": null,
   "date": "2016-01-20T00:00:00Z",
   "uri": "https://manganel.me/chapter/skip-beat_110/chapter-19"
  },
  {
   "name": 18,
   "slug": null,
   "date": "2016-01-20T00:00:00Z",
   "uri": "https://manganel.me/chapter/skip-beat_110/chapter-18"
  },
  {
   "name": 17,
   "slug": null,
   "date": "2016-01-20T00:00:00Z",
   "uri": "https://manganel.me/chapter/skip-beat_110/chapter-17"
  },
  {
   "name": 16,
   "slug": null,
   "date": "2016-01-20T00:00:00Z",
   "uri": "https://manganel.me/chapter/skip-beat_110/chapter-16"
  },
  {
   "name": 15,
   "slug": null,
   "date": "2016-01-20T00:00:00Z",
   "uri": "https://manganel.me/chapter/skip-beat_110/chapter-15"
  },
  {
   "name": 14,
   "slug": null,
   "date": "2016-01-20T00:00:00Z",
   "uri": "https://manganel.me/chapter/skip-beat_110/chapter-14"
  },
  {
   "name": 13,
   "slug": null,
   "date": "2016-01-20T00:00:00Z",
   "uri": "https://manganel.me/chapter/skip-beat_110/chapter-13"
  },
  {
   "name": 12,
   "slug": null,
   "date": "2016-01-20T00:00:00Z",
   "uri": "https://manganel.me/chapter/skip-beat_110/chapter-12"
  },
  {
   "name": 11,
   "slug": null,
   "date": "2016-01-20T00:00:00Z",
   "uri": "https://manganel.me/chapter/skip-beat_110/chapter-11"
  },
  {
   "name": 10,
   "slug": null,
   "date": "2016-01-20T00:00:00Z",
   "uri": "https://manganel.me/chapter/skip-beat_110/chapter-10"
  },
  {
   "name": 9,
   "slug": null,
   "date": "2016-01-20T00:00:00Z",
   "uri": "https://manganel.me/chapter/skip-beat_110/chapter-9"
  },
  {
   "name": 8,
   "slug": null,
   "date": "2016-01-20T00:00:00Z",
   "uri": "https://manganel.me/chapter/skip-beat_110/chapter-8"
  },
  {
   "name": 7,
   "slug": null,
   "date": "2016-01-20T00:00:00Z",
   "uri": "https://manganel.me/chapter/skip-beat_110/chapter-7"
  },
  {
   "name": 6,
   "slug": null,
   "date": "2016-01-20T00:00:00Z",
   "uri": "https://manganel.me/chapter/skip-beat_110/chapter-6"
  },
  {
   "name": 5,
   "slug": null,
   "date": "2016-01-20T00:00:00Z",
   "uri": "https://manganel.me/chapter/skip-beat_110/chapter-5"
  },
  {
   "name": 4,
   "slug": null,
   "date": "2016-01-20T00:00:00Z",
   "uri": "https://manganel.me/chapter/skip-beat_110/chapter-4"
  },
  {
   "name": 3,
   "slug": null,
   "date": "2016-01-20T00:00:00Z",
   "uri": "https://manganel.me/chapter/skip-beat_110/chapter-3"
  },
  {
   "name": 2,
   "slug": null,
   "date": "2016-01-20T00:00:00Z",
   "uri": "https://manganel.me/chapter/skip-beat_110/chapter-2"
  },
  {
   "name": 1,
   "slug": null,
   "date": "2016-01-20T00:00:00Z",
   "uri": "https://manganel.me/chapter/skip-beat_110/chapter-1"
  }
 ]
}